cdisc_library_client/__init__.py
cdisc_library_client/custom_exceptions.py
cdisc_library_client/library_client.py
cdisc_library_client-0.1.6.dist-info/LICENSE
cdisc_library_client-0.1.6.dist-info/METADATA
cdisc_library_client-0.1.6.dist-info/WHEEL
cdisc_library_client-0.1.6.dist-info/top_level.txt
cdisc_library_client-0.1.6.dist-info/RECORD
