Metadata-Version: 2.1
Name: cdisc-library-client
Version: 0.1.6
Summary: A CDISC Library client
Home-page: https://github.com/cdisc-org/cdisc-library-client
Author: CDISC
Author-email: nhaydel@cdisc.org
License: UNKNOWN
Platform: UNKNOWN
Classifier: Programming Language :: Python :: 3
Classifier: Operating System :: OS Independent
Requires-Dist: requests>=2.22.0
